{
    "FileState":                 { "h": 271, "s": 55, "l": 29 },
    "File":                      { "h": 271, "s": 55, "l": 29 },
    "DirectoryListing":          { "h": 271, "s": 55, "l": 29 },
    "DirectoryListingState":     { "h": 271, "s": 55, "l": 29 },
    "SingleToolchainResolution": { "h":   7, "s": 55, "l": 29 },
    "SingleToolchainResolution": { "h":   7, "s": 55, "l": 29 },
    "ToolchainResolution":       { "h":   7, "s": 55, "l": 29 },
    "Glob":                      { "h": 233, "s": 55, "l": 29 },
    "ConfiguredTarget":          { "h": 117, "s": 55, "l": 29 },
    "TargetCompletion":          { "h": 198, "s": 55, "l": 29 },
    "PackageLookup":             { "h": 117, "s": 55, "l": 29 },
    "ContainingPackageLookup":   { "h": 117, "s": 55, "l": 29 },
    "Artifact":                  { "h":  71, "s": 55, "l": 29 },
    "ArtifactNestedSet":         { "h":  71, "s": 55, "l": 29 },
    "ActionExecution":           { "h": 318, "s": 55, "l": 29 }
}
